{"address1": "4250 Congress Street", "address2": "Suite 900", "city": "Charlotte", "state": "NC", "zip": "28209", "country": "United States", "phone": "980 299 5700", "fax": "980 299 5512", "website": "https://www.albemarle.com", "industry": "Specialty Chemicals", "industryKey": "specialty-chemicals", "industryDisp": "Specialty Chemicals", "sector": "Basic Materials", "sectorKey": "basic-materials", "sectorDisp": "Basic Materials", "longBusinessSummary": "Albemarle Corporation provides energy storage solutions worldwide. It operates through three segments: Energy Storage, Specialties, and Ketjen. The Energy Storage segment offers lithium compounds, including lithium carbonate, lithium hydroxide, and lithium chloride for use in lithium batteries used in consumer electronics and electric vehicles, power grids and solar panels, high performance greases, specialty glass used in consumer appliances and electronics, organic synthesis processes in the areas of steroid chemistry and vitamins, and various life science applications, as well as intermediates in the pharmaceutical industry; technical services, including handling and use of reactive lithium products; and recycling services for lithium-containing by-products. The Specialties segment provides bromine and highly specialized lithium solutions for various industries, such as energy, mobility, connectivity, and health comprising fire safety compounds; bromine-based specialty chemicals products, including elemental bromine, alkyl bromides, inorganic bromides, brominated powdered activated carbon, and various bromine fine chemicals; lithium specialties, such as butyllithium and lithium aluminum hydride; cesium products for the chemical and pharmaceutical industries; and zirconium, barium, and titanium products for pyrotechnical applications that include airbag initiators. The Ketjen segment offers clean fuels technologies, including hydroprocessing catalysts together with isomerization and akylation catalysts; fluidized catalytic cracking catalysts and additives; and performance catalyst solutions comprising organometallics and curatives. It serves grid storage, automotive, aerospace, conventional energy, electronics, construction, agriculture and food, pharmaceuticals and medical device industries. Albemarle Corporation was founded in 1887 and is headquartered in Charlotte, North Carolina.", "fullTimeEmployees": 8300, "companyOfficers": [{"maxAge": 1, "name": "Mr. Jerry Kent Masters Jr.", "age": 64, "title": "Chairman, President & CEO", "yearBorn": 1960, "fiscalYear": 2024, "totalPay": 3987611, "exercisedValue": 0, "unexercisedValue": 0}, {"maxAge": 1, "name": "Mr. Neal R. Sheorey", "age": 47, "title": "Executive VP & CFO", "yearBorn": 1977, "fiscalYear": 2024, "totalPay": 1387159, "exercisedValue": 0, "unexercisedValue": 0}, {"maxAge": 1, "name": "Mr. Netha N. Johnson Jr.", "age": 53, "title": "Executive VP & COO", "yearBorn": 1971, "fiscalYear": 2024, "totalPay": 1238910, "exercisedValue": 0, "unexercisedValue": 52541}, {"maxAge": 1, "name": "Ms. Melissa H. Anderson", "age": 59, "title": "Executive VP and Chief People & Transformation Officer", "yearBorn": 1965, "fiscalYear": 2024, "totalPay": 1142580, "exercisedValue": 0, "unexercisedValue": 0}, {"maxAge": 1, "name": "Mr. Eric W. Norris", "age": 57, "title": "Executive VP & Chief Commercial Officer", "yearBorn": 1967, "fiscalYear": 2024, "totalPay": 1357962, "exercisedValue": 0, "unexercisedValue": 52541}, {"maxAge": 1, "name": "Mr. Donald J. LaBauve Jr.", "age": 57, "title": "Chief Accounting Officer, VP, Corporate Controller & CFO of Lithium Global Business Unit", "yearBorn": 1967, "fiscalYear": 2024, "totalPay": 440431, "exercisedValue": 0, "unexercisedValue": 189680}, {"maxAge": 1, "name": "Ms. Meredith H. Bandy C.F.A.", "title": "Vice President of Investor Relations & Sustainability", "fiscalYear": 2024, "exercisedValue": 0, "unexercisedValue": 0}, {"maxAge": 1, "name": "Mr. Ander  Krupa", "title": "Interim VP, General Counsel, Corporate Secretary & Chief Compliance Officer", "fiscalYear": 2024, "exercisedValue": 0, "unexercisedValue": 0}, {"maxAge": 1, "name": "Ms. Cynthia Renee Lima", "age": 62, "title": "Senior VP and Chief External Affairs & Communications Officer", "yearBorn": 1962, "fiscalYear": 2024, "exercisedValue": 0, "unexercisedValue": 0}, {"maxAge": 1, "name": "Mr. Brian  Tessin", "title": "Chief Tax Counsel & VP of Tax", "fiscalYear": 2024, "exercisedValue": 0, "unexercisedValue": 0}], "auditRisk": 6, "boardRisk": 8, "compensationRisk": 10, "shareHolderRightsRisk": 8, "overallRisk": 9, "governanceEpochDate": 1748736000, "compensationAsOfEpochDate": 1735603200, "irWebsite": "http://phx.corporate-ir.net/phoenix.zhtml?c=117031&p=irol-IRHome", "executiveTeam": [], "maxAge": 86400, "priceHint": 2, "previousClose": 74.27, "open": 70.3, "dayLow": 70.2154, "dayHigh": 71.928, "regularMarketPreviousClose": 74.27, "regularMarketOpen": 70.3, "regularMarketDayLow": 70.2154, "regularMarketDayHigh": 71.928, "dividendRate": 1.62, "dividendYield": 2.58, "exDividendDate": 1749772800, "payoutRatio": 0.5797, "fiveYearAvgDividendYield": 1.17, "beta": 1.614, "forwardPE": 38.576088, "volume": 4056387, "regularMarketVolume": 4056387, "averageVolume": 3545296, "averageVolume10days": 4129980, "averageDailyVolume10Day": 4129980, "bid": 0.0, "ask": 72.3, "bidSize": 3, "askSize": 2, "marketCap": 8351578112, "fiftyTwoWeekLow": 49.43, "fiftyTwoWeekHigh": 113.91, "priceToSalesTrailing12Months": 1.6395991, "fiftyDayAverage": 61.0416, "twoHundredDayAverage": 80.121, "trailingAnnualDividendRate": 1.615, "trailingAnnualDividendYield": 0.021744985, "currency": "USD", "tradeable": false, "enterpriseValue": 12010344448, "profitMargins": -0.22391, "floatShares": 117097318, "sharesOutstanding": 117661000, "sharesShort": 18702937, "sharesShortPriorMonth": 18833138, "sharesShortPreviousMonthDate": 1747267200, "dateShortInterest": 1749772800, "sharesPercentSharesOut": 0.159, "heldPercentInsiders": 0.00402, "heldPercentInstitutions": 0.98374003, "shortRatio": 5.36, "shortPercentOfFloat": 0.23969999, "impliedSharesOutstanding": 117661000, "bookValue": 66.239, "priceToBook": 1.0715742, "lastFiscalYearEnd": 1735603200, "nextFiscalYearEnd": 1767139200, "mostRecentQuarter": 1743379200, "earningsQuarterlyGrowth": 15.891, "netIncomeToCommon": -1307299968, "trailingEps": -11.12, "forwardEps": 1.84, "lastSplitFactor": "2:1", "lastSplitDate": 1172793600, "enterpriseToRevenue": 2.358, "enterpriseToEbitda": 62.687, "52WeekChange": -0.25667608, "SandP52WeekChange": 0.1116153, "lastDividendValue": 0.405, "lastDividendDate": 1749772800, "quoteType": "EQUITY", "currentPrice": 70.98, "targetHighPrice": 200.0, "targetLowPrice": 58.0, "targetMeanPrice": 81.8956, "targetMedianPrice": 75.0, "recommendationMean": 2.51852, "recommendationKey": "hold", "numberOfAnalystOpinions": 25, "totalCash": 1518510976, "totalCashPerShare": 12.906, "ebitda": 191592992, "totalDebt": 3673838080, "quickRatio": 1.196, "currentRatio": 2.112, "totalRevenue": 5093670912, "debtToEquity": 35.757, "revenuePerShare": 43.33, "returnOnAssets": -0.01509, "returnOnEquity": -0.09992, "grossProfits": 200200000, "freeCashflow": -349651872, "operatingCashflow": 1149496960, "revenueGrowth": -0.209, "grossMargins": 0.039300002, "ebitdaMargins": 0.037609998, "operatingMargins": 0.01898, "financialCurrency": "USD", "symbol": "ALB", "language": "en-US", "region": "US", "typeDisp": "Equity", "quoteSourceName": "Nasdaq Real Time Price", "triggerable": true, "customPriceAlertConfidence": "HIGH", "shortName": "Albemarle Corporation", "longName": "Albemarle Corporation", "regularMarketChangePercent": -4.42977, "regularMarketPrice": 70.98, "exchange": "NYQ", "messageBoardId": "finmb_18671", "exchangeTimezoneName": "America/New_York", "exchangeTimezoneShortName": "EDT", "gmtOffSetMilliseconds": -14400000, "market": "us_market", "esgPopulated": false, "corporateActions": [], "preMarketTime": 1752490420, "regularMarketTime": 1752264002, "fiftyDayAverageChangePercent": 0.16281362, "twoHundredDayAverageChange": -9.140999, "twoHundredDayAverageChangePercent": -0.11408992, "sourceInterval": 15, "exchangeDataDelayedBy": 0, "averageAnalystRating": "2.5 - Hold", "cryptoTradeable": false, "marketState": "PRE", "hasPrePostMarketData": true, "firstTradeDateMilliseconds": 761927400000, "preMarketChange": 1.2299957, "preMarketChangePercent": 1.7328764, "preMarketPrice": 72.21, "regularMarketChange": -3.28999, "regularMarketDayRange": "70.2154 - 71.928", "fullExchangeName": "NYSE", "averageDailyVolume3Month": 3545296, "fiftyTwoWeekLowChange": 21.550003, "fiftyTwoWeekLowChangePercent": 0.43597013, "fiftyTwoWeekRange": "49.43 - 113.91", "fiftyTwoWeekHighChange": -42.93, "fiftyTwoWeekHighChangePercent": -0.37687647, "fiftyTwoWeekChangePercent": -25.667608, "dividendDate": 1751328000, "earningsTimestamp": 1753905600, "earningsTimestampStart": 1753905600, "earningsTimestampEnd": 1753905600, "earningsCallTimestampStart": 1746100800, "earningsCallTimestampEnd": 1746100800, "isEarningsDateEstimate": false, "epsTrailingTwelveMonths": -11.12, "epsForward": 1.84, "epsCurrentYear": -1.68307, "priceEpsCurrentYear": -42.172935, "fiftyDayAverageChange": 9.938404, "displayName": "Albemarle", "trailingPegRatio": null}