{"address1": "26 North Euclid Avenue", "city": "Pasadena", "state": "CA", "zip": "91101-6104", "country": "United States", "phone": "626 578 0777", "fax": "626 578 0896", "website": "https://www.are.com", "industry": "REIT - Office", "industryKey": "reit-office", "industryDisp": "REIT - Office", "sector": "Real Estate", "sectorKey": "real-estate", "sectorDisp": "Real Estate", "longBusinessSummary": "Alexandria Real Estate Equities, Inc. (NYSE: ARE), an S&P 500 company, is a best-in-class, mission-driven life science REIT making a positive and lasting impact on the world. With our founding in 1994, Alexandria pioneered the life science real estate niche. Alexandria is the preeminent and longest-tenured owner, operator, and developer of collaborative Megacampus ecosystems in AAA life science innovation cluster locations, including Greater Boston, the San Francisco Bay Area, San Diego, Seattle, Maryland, Research Triangle, and New York City. As of March 31, 2025, Alexandria has a total market capitalization of $28.8 billion and an asset base in North America that includes 39.6 million RSF of operating properties and 4.0 million RSF of Class A/A+ properties undergoing construction. Alexandria has a longstanding and proven track record of developing Class A/A+ properties clustered in highly dynamic and collaborative Megacampus environments that enhance our tenants' ability to successfully recruit and retain world-class talent and inspire productivity, efficiency, creativity, and success. Alexandria also provides strategic capital to transformative life science companies through our venture capital platform. We believe our unique business model and diligent underwriting ensure a high-quality and diverse tenant base that results in higher occupancy levels, longer lease terms, higher rental income, higher returns, and greater long-term asset value.", "fullTimeEmployees": 552, "companyOfficers": [{"maxAge": 1, "name": "Mr. Joel S. Marcus CPA, J.D.", "age": 77, "title": "Founder & Executive Chairman", "yearBorn": 1947, "fiscalYear": 2024, "totalPay": 6438721, "exercisedValue": 0, "unexercisedValue": 0}, {"maxAge": 1, "name": "Mr. Peter M. Moglia", "age": 57, "title": "CEO & Chief Investment Officer", "yearBorn": 1967, "fiscalYear": 2024, "totalPay": 2683357, "exercisedValue": 0, "unexercisedValue": 0}, {"maxAge": 1, "name": "Mr. Daniel J. Ryan", "age": 58, "title": "Co-President & Regional Market Director of San Diego", "yearBorn": 1966, "fiscalYear": 2024, "totalPay": 2586000, "exercisedValue": 0, "unexercisedValue": 0}, {"maxAge": 1, "name": "Mr. Hunter L. Kass", "age": 41, "title": "Co-President & Regional Market Director of Greater Boston", "yearBorn": 1983, "fiscalYear": 2024, "totalPay": 2496000, "exercisedValue": 0, "unexercisedValue": 0}, {"maxAge": 1, "name": "Mr. Marc E. Binda CPA", "age": 47, "title": "CFO & Treasurer", "yearBorn": 1977, "fiscalYear": 2024, "totalPay": 1648598, "exercisedValue": 0, "unexercisedValue": 0}, {"maxAge": 1, "name": "Mr. Lawrence J. Diamond", "age": 65, "title": "Co-COO & Regional Market Director of Maryland", "yearBorn": 1959, "fiscalYear": 2024, "totalPay": 1221528, "exercisedValue": 0, "unexercisedValue": 0}, {"maxAge": 1, "name": "Mr. Joseph  Hakman", "age": 52, "title": "Co-COO & Chief Strategic Transactions Officer", "yearBorn": 1972, "fiscalYear": 2024, "exercisedValue": 0, "unexercisedValue": 0}, {"maxAge": 1, "name": "Mr. Andres R. Gavinet CPA", "age": 55, "title": "Chief Accounting Officer", "yearBorn": 1969, "fiscalYear": 2024, "exercisedValue": 0, "unexercisedValue": 0}, {"maxAge": 1, "name": "Mr. Gregory C. Thomas", "title": "Chief Technology Officer", "fiscalYear": 2024, "exercisedValue": 0, "unexercisedValue": 0}, {"maxAge": 1, "name": "Ms. Jackie B. Clem J.D.", "age": 55, "title": "General Counsel & Secretary", "yearBorn": 1969, "fiscalYear": 2024, "exercisedValue": 0, "unexercisedValue": 0}], "auditRisk": 7, "boardRisk": 9, "compensationRisk": 3, "shareHolderRightsRisk": 8, "overallRisk": 8, "governanceEpochDate": 1754006400, "compensationAsOfEpochDate": 1735603200, "executiveTeam": [], "maxAge": 86400, "priceHint": 2, "previousClose": 74.56, "open": 74.55, "dayLow": 73.97, "dayHigh": 75.38, "regularMarketPreviousClose": 74.56, "regularMarketOpen": 74.55, "regularMarketDayLow": 73.97, "regularMarketDayHigh": 75.38, "dividendRate": 5.28, "dividendYield": 7.11, "exDividendDate": 1751241600, "payoutRatio": 6.8946996, "fiveYearAvgDividendYield": 3.68, "beta": 1.253, "forwardPE": 21.572674, "volume": 914620, "regularMarketVolume": 914620, "averageVolume": 1740917, "averageVolume10days": 1640710, "averageDailyVolume10Day": 1640710, "bid": 74.11, "ask": 74.85, "bidSize": 1, "askSize": 3, "marketCap": 12669204480, "fiftyTwoWeekLow": 67.37, "fiftyTwoWeekHigh": 125.63, "priceToSalesTrailing12Months": 4.0894837, "fiftyDayAverage": 75.272, "twoHundredDayAverage": 90.1661, "trailingAnnualDividendRate": 5.26, "trailingAnnualDividendYield": 0.070547216, "currency": "USD", "tradeable": false, "enterpriseValue": 30536026112, "profitMargins": -0.00331, "floatShares": 154077020, "sharesOutstanding": 170720992, "sharesShort": 7063384, "sharesShortPriorMonth": 6360859, "sharesShortPreviousMonthDate": 1749772800, "dateShortInterest": 1752537600, "sharesPercentSharesOut": 0.0414, "heldPercentInsiders": 0.00987, "heldPercentInstitutions": 0.97875, "shortRatio": 3.85, "shortPercentOfFloat": 0.056500003, "impliedSharesOutstanding": 180638000, "bookValue": 100.944, "priceToBook": 0.73516005, "lastFiscalYearEnd": 1735603200, "nextFiscalYearEnd": 1767139200, "mostRecentQuarter": 1751241600, "netIncomeToCommon": -21458000, "trailingEps": -0.13, "forwardEps": 3.44, "enterpriseToRevenue": 9.857, "enterpriseToEbitda": 15.432, "52WeekChange": -0.33497626, "SandP52WeekChange": 0.19554341, "lastDividendValue": 1.32, "lastDividendDate": 1751241600, "quoteType": "EQUITY", "currentPrice": 74.21, "targetHighPrice": 144.0, "targetLowPrice": 71.0, "targetMeanPrice": 98.83333, "targetMedianPrice": 93.0, "recommendationMean": 2.41667, "recommendationKey": "buy", "numberOfAnalystOpinions": 12, "totalCash": 520544992, "totalCashPerShare": 3.01, "ebitda": 1978750976, "totalDebt": 13657519104, "quickRatio": 1.403, "currentRatio": 1.62, "totalRevenue": 3097996032, "debtToEquity": 62.825, "revenuePerShare": 18.091, "returnOnAssets": 0.012, "returnOnEquity": 0.00784, "grossProfits": 2173470976, "freeCashflow": 1351669632, "operatingCashflow": 1419760000, "revenueGrowth": -0.018, "grossMargins": 0.70157, "ebitdaMargins": 0.63872004, "operatingMargins": 0.20363002, "financialCurrency": "USD", "symbol": "ARE", "language": "en-US", "region": "US", "typeDisp": "Equity", "quoteSourceName": "Nasdaq Real Time Price", "triggerable": true, "customPriceAlertConfidence": "HIGH", "exchange": "NYQ", "messageBoardId": "finmb_365138", "exchangeTimezoneName": "America/New_York", "exchangeTimezoneShortName": "EDT", "corporateActions": [], "postMarketTime": 1754696351, "regularMarketTime": 1754683202, "shortName": "Alexandria Real Estate Equities", "longName": "Alexandria Real Estate Equities, Inc.", "gmtOffSetMilliseconds": -14400000, "market": "us_market", "esgPopulated": false, "marketState": "CLOSED", "fiftyDayAverageChange": -1.0620041, "fiftyDayAverageChangePercent": -0.014108886, "twoHundredDayAverageChange": -15.9561, "twoHundredDayAverageChangePercent": -0.1769634, "sourceInterval": 15, "exchangeDataDelayedBy": 0, "averageAnalystRating": "2.4 - Buy", "cryptoTradeable": false, "regularMarketChangePercent": -0.469419, "regularMarketPrice": 74.21, "hasPrePostMarketData": true, "firstTradeDateMilliseconds": 864826200000, "postMarketChangePercent": 0.539013, "postMarketPrice": 74.61, "postMarketChange": 0.400002, "regularMarketChange": -0.349998, "regularMarketDayRange": "73.97 - 75.38", "fullExchangeName": "NYSE", "averageDailyVolume3Month": 1740917, "fiftyTwoWeekLowChange": 6.8399963, "fiftyTwoWeekLowChangePercent": 0.10152881, "fiftyTwoWeekRange": "67.37 - 125.63", "fiftyTwoWeekHighChange": -51.42, "fiftyTwoWeekHighChangePercent": -0.40929714, "fiftyTwoWeekChangePercent": -33.497627, "dividendDate": 1752537600, "earningsTimestamp": 1753128000, "earningsTimestampStart": 1753128000, "earningsTimestampEnd": 1753128000, "earningsCallTimestampStart": 1753207200, "earningsCallTimestampEnd": 1753207200, "isEarningsDateEstimate": false, "epsTrailingTwelveMonths": -0.13, "epsForward": 3.44, "epsCurrentYear": 2.58796, "priceEpsCurrentYear": 28.675095, "displayName": "Alexandria Real Estate Equities", "trailingPegRatio": null}