{"address1": "1 Water Street", "city": "Camden", "state": "NJ", "zip": "08102-1658", "country": "United States", "phone": "856 955 4001", "website": "https://www.amwater.com", "industry": "Utilities - Regulated Water", "industryKey": "utilities-regulated-water", "industryDisp": "Utilities - Regulated Water", "sector": "Utilities", "sectorKey": "utilities", "sectorDisp": "Utilities", "longBusinessSummary": "American Water Works Company, Inc., through its subsidiaries, provides water and wastewater services in the United States. It offers water and wastewater services on military installations; and undertakes contracts with municipal customers, primarily to operate and manage water and wastewater facilities, as well as offers other related services. The company also operates approximately 80 surface water treatment plants; 520 groundwater treatment plants; 190 wastewater treatment plants; 54,500 miles of transmission, distribution, and collection mains and pipes; 1,200 groundwater wells; 1,800 water and wastewater pumping stations; 1,100 treated water storage facilities; and 75 dams. In addition, it offers water and wastewater services to 14 states serving approximately 3.5 million active customers. The company serves residential customers; commercial customers, including food and beverage providers, commercial property developers and proprietors, and energy suppliers; fire service and private fire customers; industrial customers, such as large-scale manufacturers, mining, and production operations; public authorities comprising government buildings and other public sector facilities, such as schools and universities; and other utilities and community water and wastewater systems. American Water Works Company, Inc. was founded in 1886 and is headquartered in Camden, New Jersey.", "fullTimeEmployees": 6700, "companyOfficers": [{"maxAge": 1, "name": "Mr. John C. Griffith", "age": 57, "title": "CEO, President & Director", "yearBorn": 1967, "fiscalYear": 2024, "totalPay": 2403563, "exercisedValue": 0, "unexercisedValue": 0}, {"maxAge": 1, "name": "Ms. Cheryl D. Norton", "age": 59, "title": "Executive VP & COO", "yearBorn": 1965, "fiscalYear": 2024, "totalPay": 1713887, "exercisedValue": 0, "unexercisedValue": 0}, {"maxAge": 1, "name": "Mr. Stacy A. Mitchell", "age": 48, "title": "Executive VP & General Counsel", "yearBorn": 1976, "fiscalYear": 2024, "totalPay": 994879, "exercisedValue": 0, "unexercisedValue": 0}, {"maxAge": 1, "name": "Ms. Melissa K. Wikle", "age": 58, "title": "Senior VP & Chief Accounting Officer", "yearBorn": 1966, "fiscalYear": 2024, "exercisedValue": 0, "unexercisedValue": 0}, {"maxAge": 1, "name": "Ms. Deborah A. Degillio", "age": 52, "title": "Chief Technology & Information Officer", "yearBorn": 1972, "fiscalYear": 2024, "exercisedValue": 0, "unexercisedValue": 0}, {"maxAge": 1, "name": "Ms. Maureen  Duffy", "age": 54, "title": "Executive VP of Communications & External Affairs", "yearBorn": 1970, "fiscalYear": 2024, "exercisedValue": 0, "unexercisedValue": 0}, {"maxAge": 1, "name": "Mr. Nicholas  Santillo Jr., C.P.P.", "title": "Vice President of Digital Infrastructure & Security and Interim Head of Innovation & Technology", "fiscalYear": 2024, "exercisedValue": 0, "unexercisedValue": 0}, {"maxAge": 1, "name": "Mr. Matthew  Prine", "title": "Chief Customer Officer", "fiscalYear": 2024, "exercisedValue": 0, "unexercisedValue": 0}, {"maxAge": 1, "name": "Mr. Mike  Doran", "title": "Deputy Chief Operating Officer", "fiscalYear": 2024, "exercisedValue": 0, "unexercisedValue": 0}, {"maxAge": 1, "name": "Ruben  Rodriguez", "title": "Senior Director of External Communications", "fiscalYear": 2024, "exercisedValue": 0, "unexercisedValue": 0}], "auditRisk": 6, "boardRisk": 2, "compensationRisk": 3, "shareHolderRightsRisk": 4, "overallRisk": 2, "governanceEpochDate": 1754006400, "compensationAsOfEpochDate": 1735603200, "irWebsite": "http://ir.amwater.com/phoenix.zhtml?c=215126&p=irol-irhome", "executiveTeam": [], "maxAge": 86400, "priceHint": 2, "previousClose": 144.42, "open": 144.83, "dayLow": 144.575, "dayHigh": 145.64, "regularMarketPreviousClose": 144.42, "regularMarketOpen": 144.83, "regularMarketDayLow": 144.575, "regularMarketDayHigh": 145.64, "dividendRate": 3.31, "dividendYield": 2.28, "exDividendDate": 1754956800, "payoutRatio": 0.56259996, "fiveYearAvgDividendYield": 1.81, "beta": 0.644, "trailingPE": 26.19099, "forwardPE": 25.501755, "volume": 1986675, "regularMarketVolume": 1986675, "averageVolume": 1388751, "averageVolume10days": 2139370, "averageDailyVolume10Day": 2139370, "bid": 145.07, "ask": 145.11, "bidSize": 1, "askSize": 2, "marketCap": 28359591936, "fiftyTwoWeekLow": 118.74, "fiftyTwoWeekHigh": 155.5, "priceToSalesTrailing12Months": 5.738485, "fiftyDayAverage": 141.5034, "twoHundredDayAverage": 137.1638, "trailingAnnualDividendRate": 3.123, "trailingAnnualDividendYield": 0.02162443, "currency": "USD", "tradeable": false, "enterpriseValue": 43256528896, "profitMargins": 0.21914, "floatShares": 194673251, "sharesOutstanding": 195099008, "sharesShort": 6336729, "sharesShortPriorMonth": 5560218, "sharesShortPreviousMonthDate": 1749772800, "dateShortInterest": 1752537600, "sharesPercentSharesOut": 0.0325, "heldPercentInsiders": 0.0014200001, "heldPercentInstitutions": 0.94206, "shortRatio": 5.45, "shortPercentOfFloat": 0.0419, "impliedSharesOutstanding": 195099008, "bookValue": 54.752, "priceToBook": 2.6548803, "lastFiscalYearEnd": 1735603200, "nextFiscalYearEnd": 1767139200, "mostRecentQuarter": 1751241600, "earningsQuarterlyGrowth": 0.043, "netIncomeToCommon": 1083000064, "trailingEps": 5.55, "forwardEps": 5.7, "enterpriseToRevenue": 8.753, "enterpriseToEbitda": 16.219, "52WeekChange": 0.019640803, "SandP52WeekChange": 0.19554341, "lastDividendValue": 0.828, "lastDividendDate": 1747094400, "quoteType": "EQUITY", "currentPrice": 145.36, "targetHighPrice": 159.0, "targetLowPrice": 116.0, "targetMeanPrice": 143.0, "targetMedianPrice": 146.0, "recommendationMean": 2.76923, "recommendationKey": "hold", "numberOfAnalystOpinions": 10, "totalCash": 175000000, "totalCashPerShare": 0.897, "ebitda": 2667000064, "totalDebt": 15072000000, "quickRatio": 0.265, "currentRatio": 0.351, "totalRevenue": 4942000128, "debtToEquity": 141.097, "revenuePerShare": 25.344, "returnOnAssets": 0.03499, "returnOnEquity": 0.10396, "grossProfits": 2979000064, "freeCashflow": -1340499968, "operatingCashflow": 1950000000, "earningsGrowth": 0.042, "revenueGrowth": 0.111, "grossMargins": 0.60279, "ebitdaMargins": 0.53966, "operatingMargins": 0.38636002, "financialCurrency": "USD", "symbol": "AWK", "language": "en-US", "region": "US", "typeDisp": "Equity", "quoteSourceName": "Delayed Quote", "triggerable": true, "customPriceAlertConfidence": "HIGH", "regularMarketChangePercent": 0.650881, "regularMarketPrice": 145.36, "postMarketChangePercent": 1.4962872, "postMarketPrice": 147.535, "postMarketChange": 2.175003, "regularMarketChange": 0.940002, "regularMarketDayRange": "144.575 - 145.64", "fullExchangeName": "NYSE", "averageDailyVolume3Month": 1388751, "fiftyTwoWeekLowChange": 26.620003, "fiftyTwoWeekLowChangePercent": 0.22418733, "fiftyTwoWeekRange": "118.74 - 155.5", "fiftyTwoWeekHighChange": -10.139999, "fiftyTwoWeekHighChangePercent": -0.065209, "fiftyTwoWeekChangePercent": 1.9640803, "dividendDate": 1756857600, "earningsTimestamp": 1761768000, "earningsTimestampStart": 1761768000, "earningsTimestampEnd": 1761768000, "earningsCallTimestampStart": 1761829200, "earningsCallTimestampEnd": 1761829200, "isEarningsDateEstimate": false, "epsTrailingTwelveMonths": 5.55, "epsForward": 5.7, "epsCurrentYear": 5.70254, "priceEpsCurrentYear": 25.490396, "fiftyDayAverageChange": 3.856598, "fiftyDayAverageChangePercent": 0.027254453, "twoHundredDayAverageChange": 8.1961975, "twoHundredDayAverageChangePercent": 0.059754815, "sourceInterval": 15, "exchangeDataDelayedBy": 0, "averageAnalystRating": "2.8 - Hold", "cryptoTradeable": false, "hasPrePostMarketData": true, "firstTradeDateMilliseconds": 1208957400000, "corporateActions": [{"header": "Dividend", "message": "AWK announced a cash dividend of 0.827 with an ex-date of Aug. 12, 2025", "meta": {"eventType": "DIVIDEND", "dateEpochMs": 1754971200000, "amount": "0.827"}}], "postMarketTime": 1754693714, "regularMarketTime": 1754683202, "exchange": "NYQ", "messageBoardId": "finmb_250885", "exchangeTimezoneName": "America/New_York", "exchangeTimezoneShortName": "EDT", "gmtOffSetMilliseconds": -14400000, "market": "us_market", "esgPopulated": false, "shortName": "American Water Works Company, I", "longName": "American Water Works Company, Inc.", "marketState": "CLOSED", "displayName": "American Water Works Company", "trailingPegRatio": 3.7682}