{"address1": "1 Becton Drive", "city": "Franklin Lakes", "state": "NJ", "zip": "07417-1880", "country": "United States", "phone": "201 847 6800", "website": "https://www.bd.com", "industry": "Medical Instruments & Supplies", "industryKey": "medical-instruments-supplies", "industryDisp": "Medical Instruments & Supplies", "sector": "Healthcare", "sectorKey": "healthcare", "sectorDisp": "Healthcare", "longBusinessSummary": "Becton, Dickinson and Company develops, manufactures, and sells medical supplies, devices, laboratory equipment, and diagnostic products for healthcare institutions, physicians, life science researchers, clinical laboratories, pharmaceutical industry, and the general public worldwide. The BD Medical segment provides peripheral intravenous (IV) and advanced peripheral catheters, central lines, acute dialysis catheters, vascular access technology, vascular care and preparation products, needle-free IV connectors and extensions sets, closed-system drug transfer devices, hazardous drug detections, hypodermic syringes and needles, anesthesia needles and trays, enteral syringes, and sharps disposal systems; IV medication safety and infusion therapy delivery systems, medication compounding workflow systems, automated medication dispensing and supply management systems, informatics and analytics and pharmacy automation systems, and medication inventory optimization and tracking systems; hemodynamic monitoring systems; and prefillable drug delivery systems. The BD Life Sciences segment offers specimen and blood collection products; automated blood and tuberculosis culturing, molecular testing, microorganism identification and drug susceptibility, and liquid-based cytology systems, as well as rapid diagnostic assays, microbiology laboratory automation products, and plated media products; and fluorescence-activated cell sorters and analyzers, antibodies and kits, reagent systems, and solutions for single-cell gene expression analysis, as well as clinical oncology, immunological, and transplantation diagnostic/monitoring reagents and analyzers. The BD Interventional segment provides hernia and soft tissue repair, biological and bioresorbable grafts, biosurgery, and other surgical products; surgical infection prevention; peripheral intervention products; and urology and critical care products. The company was founded in 1897 and is headquartered in Franklin Lakes, New Jersey.", "fullTimeEmployees": 70000, "companyOfficers": [{"maxAge": 1, "name": "Mr. Thomas E. Polen Jr.", "age": 51, "title": "President, CEO & Chairman", "yearBorn": 1973, "fiscalYear": 2024, "totalPay": 3733112, "exercisedValue": 0, "unexercisedValue": 3074976}, {"maxAge": 1, "name": "Mr. Christopher J. DelOrefice CPA", "age": 52, "title": "Executive VP & CFO", "yearBorn": 1972, "fiscalYear": 2024, "totalPay": 1777376, "exercisedValue": 0, "unexercisedValue": 14179}, {"maxAge": 1, "name": "Ms. Shana Carol Neal", "age": 58, "title": "Executive VP & Chief People Officer", "yearBorn": 1966, "fiscalYear": 2024, "totalPay": 1387319, "exercisedValue": 0, "unexercisedValue": 8320}, {"maxAge": 1, "name": "Mr. Michael  Garrison", "age": 54, "title": "Executive VP & President of Medical segment", "yearBorn": 1970, "fiscalYear": 2024, "totalPay": 1332675, "exercisedValue": 0, "unexercisedValue": 1040447}, {"maxAge": 1, "name": "Mr. Richard  Byrd", "age": 56, "title": "Executive VP & President of Interventional Segment", "yearBorn": 1968, "fiscalYear": 2024, "totalPay": 1374985, "exercisedValue": 0, "unexercisedValue": 357463}, {"maxAge": 1, "name": "Ms. Pamela L. Spikner", "age": 46, "title": "Senior VP, Chief Accounting Officer & Controller", "yearBorn": 1978, "fiscalYear": 2024, "exercisedValue": 0, "unexercisedValue": 0}, {"maxAge": 1, "name": "Ms. Elizabeth  McCombs", "age": 47, "title": "Executive VP & Chief Technology Officer", "yearBorn": 1977, "fiscalYear": 2024, "exercisedValue": 0, "unexercisedValue": 0}, {"maxAge": 1, "name": "Dr. Joseph M. Smith F.A.C.C, M.D., Ph.D.", "title": "Senior VP & Chief Scientific Officer", "fiscalYear": 2024, "exercisedValue": 0, "unexercisedValue": 0}, {"maxAge": 1, "name": "Ms. Denise Russell Fleming", "age": 53, "title": "Executive VP of Technology & Global Services and Chief Information Officer", "yearBorn": 1971, "fiscalYear": 2024, "exercisedValue": 0, "unexercisedValue": 0}, {"maxAge": 1, "name": "Mr. Greg  Rodetis", "title": "Senior VP, Treasurer & Head of Investor Relations", "fiscalYear": 2024, "exercisedValue": 0, "unexercisedValue": 0}], "auditRisk": 4, "boardRisk": 4, "compensationRisk": 7, "shareHolderRightsRisk": 1, "overallRisk": 2, "governanceEpochDate": 1754006400, "compensationAsOfEpochDate": 1735603200, "irWebsite": "http://www.bd.com/investors/", "executiveTeam": [], "maxAge": 86400, "priceHint": 2, "previousClose": 187.68, "open": 186.87, "dayLow": 187.0, "dayHigh": 193.88, "regularMarketPreviousClose": 187.68, "regularMarketOpen": 186.87, "regularMarketDayLow": 187.0, "regularMarketDayHigh": 193.88, "dividendRate": 4.16, "dividendYield": 2.15, "exDividendDate": 1757289600, "payoutRatio": 0.74410003, "fiveYearAvgDividendYield": 1.49, "beta": 0.224, "trailingPE": 35.31022, "forwardPE": 12.301335, "volume": 3805072, "regularMarketVolume": 3805072, "averageVolume": 2962414, "averageVolume10days": 3154890, "averageDailyVolume10Day": 3154890, "bid": 191.5, "ask": 193.57, "bidSize": 2, "askSize": 4, "marketCap": 55462326272, "fiftyTwoWeekLow": 163.33, "fiftyTwoWeekHigh": 251.99, "priceToSalesTrailing12Months": 2.593394, "fiftyDayAverage": 175.8514, "twoHundredDayAverage": 208.6702, "trailingAnnualDividendRate": 4.07, "trailingAnnualDividendYield": 0.02168585, "currency": "USD", "tradeable": false, "enterpriseValue": 74151395328, "profitMargins": 0.07411, "floatShares": 286486535, "sharesOutstanding": 286627008, "sharesShort": 4685009, "sharesShortPriorMonth": 3213975, "sharesShortPreviousMonthDate": 1749772800, "dateShortInterest": 1752537600, "sharesPercentSharesOut": 0.0163, "heldPercentInsiders": 0.00567, "heldPercentInstitutions": 0.91695, "shortRatio": 1.49, "shortPercentOfFloat": 0.0164, "impliedSharesOutstanding": 286607008, "bookValue": 88.7, "priceToBook": 2.1815107, "lastFiscalYearEnd": 1727654400, "nextFiscalYearEnd": 1759190400, "mostRecentQuarter": 1751241600, "earningsQuarterlyGrowth": 0.179, "netIncomeToCommon": 1584999936, "trailingEps": 5.48, "forwardEps": 15.73, "lastSplitFactor": "1025:1000", "lastSplitDate": 1648771200, "enterpriseToRevenue": 3.467, "enterpriseToEbitda": 13.729, "52WeekChange": -0.17353606, "SandP52WeekChange": 0.19554341, "lastDividendValue": 1.04, "lastDividendDate": 1749427200, "quoteType": "EQUITY", "currentPrice": 193.5, "targetHighPrice": 270.0, "targetLowPrice": 183.0, "targetMeanPrice": 211.54546, "targetMedianPrice": 197.0, "recommendationMean": 2.35714, "recommendationKey": "buy", "numberOfAnalystOpinions": 11, "totalCash": 757000000, "totalCashPerShare": 2.636, "ebitda": 5400999936, "totalDebt": 19341000704, "quickRatio": 0.453, "currentRatio": 1.103, "totalRevenue": 21386000384, "debtToEquity": 75.93, "revenuePerShare": 74.154, "returnOnAssets": 0.03374, "returnOnEquity": 0.061750002, "grossProfits": 9651000320, "freeCashflow": 3038625024, "operatingCashflow": 3254000128, "earningsGrowth": 0.19, "revenueGrowth": 0.104, "grossMargins": 0.45128, "ebitdaMargins": 0.25255, "operatingMargins": 0.18351999, "financialCurrency": "USD", "symbol": "BDX", "language": "en-US", "region": "US", "typeDisp": "Equity", "quoteSourceName": "Delayed Quote", "triggerable": true, "customPriceAlertConfidence": "HIGH", "fiftyDayAverageChange": 17.648605, "fiftyDayAverageChangePercent": 0.10036091, "twoHundredDayAverageChange": -15.170197, "twoHundredDayAverageChangePercent": -0.07269939, "sourceInterval": 15, "exchangeDataDelayedBy": 0, "averageAnalystRating": "2.4 - Buy", "cryptoTradeable": false, "longName": "Becton, Dickinson and Company", "shortName": "Becton, Dickinson and Company", "corporateActions": [{"header": "Dividend", "message": "BDX announced a cash dividend of 1.04 with an ex-date of Sep. 8, 2025", "meta": {"eventType": "DIVIDEND", "dateEpochMs": 1757304000000, "amount": "1.04"}}], "postMarketTime": 1754697316, "regularMarketTime": 1754683202, "exchange": "NYQ", "messageBoardId": "finmb_103678", "exchangeTimezoneName": "America/New_York", "exchangeTimezoneShortName": "EDT", "gmtOffSetMilliseconds": -14400000, "market": "us_market", "esgPopulated": false, "regularMarketChangePercent": 3.10103, "regularMarketPrice": 193.5, "postMarketChangePercent": -0.098192476, "postMarketPrice": 193.31, "postMarketChange": -0.19000244, "regularMarketChange": 5.82001, "regularMarketDayRange": "187.0 - 193.88", "fullExchangeName": "NYSE", "averageDailyVolume3Month": 2962414, "fiftyTwoWeekLowChange": 30.169998, "fiftyTwoWeekLowChangePercent": 0.18471804, "fiftyTwoWeekRange": "163.33 - 251.99", "fiftyTwoWeekHighChange": -58.490005, "fiftyTwoWeekHighChangePercent": -0.23211241, "fiftyTwoWeekChangePercent": -17.353607, "dividendDate": 1759190400, "earningsTimestamp": 1754539200, "earningsTimestampStart": 1762432200, "earningsTimestampEnd": 1762432200, "earningsCallTimestampStart": 1754568000, "earningsCallTimestampEnd": 1754568000, "isEarningsDateEstimate": false, "epsTrailingTwelveMonths": 5.48, "epsForward": 15.73, "epsCurrentYear": 14.3763, "priceEpsCurrentYear": 13.459653, "hasPrePostMarketData": true, "firstTradeDateMilliseconds": 99153000000, "marketState": "CLOSED", "trailingPegRatio": 0.9681}