{"address1": "1 West First Avenue", "city": "Conshohocken", "state": "PA", "zip": "19428-1800", "country": "United States", "phone": "610 727 7000", "website": "https://www.cencora.com", "industry": "Medical Distribution", "industryKey": "medical-distribution", "industryDisp": "Medical Distribution", "sector": "Healthcare", "sectorKey": "healthcare", "sectorDisp": "Healthcare", "longBusinessSummary": "Cencora, Inc. sources and distributes pharmaceutical products in the United States and internationally. The company's U.S. Healthcare Solutions segment distributes pharmaceuticals, over-the-counter healthcare products, home healthcare supplies and equipment, and related services to acute care hospitals and health systems, independent and chain retail pharmacies, mail order pharmacies, medical clinics, long-term care and alternate site pharmacies, and other customers; provides pharmacy management, staffing, and other consulting services; supply management software to retail and institutional healthcare providers; packaging solutions to institutional and retail healthcare providers; clinical trial support, product post-approval, and commercialization support services; data analytics, outcomes research, and other services for biotechnology and pharmaceutical manufacturers; pharmaceuticals, vaccines, parasiticides, diagnostics, micro feed ingredients, and other products to the companion animal and production animal markets; and sales force services to manufacturers. This segment also distributes plasma and other blood products, injectable pharmaceuticals, vaccines, and other specialty products; and offers other services to physicians who specialize in various disease states, such as oncology, as well as to other healthcare providers, including hospitals and dialysis clinics. Its International Healthcare Solutions segment provides international pharmaceutical wholesale and related service, and global commercialization services; distributes pharmaceuticals, other healthcare products, and related services to pharmacies, doctors, health centers, and hospitals; and offers specialty transportation and logistics services for the biopharmaceutical industry. The company was formerly known as AmerisourceBergen Corporation and changed its name to Cencora, Inc. in August 2023. Cencora, Inc. was founded in 1871 and is headquartered in Conshohocken, Pennsylvania.", "fullTimeEmployees": 51000, "companyOfficers": [{"maxAge": 1, "name": "Mr. Steven H. Collis", "age": 63, "title": "Executive Chairman", "yearBorn": 1961, "fiscalYear": 2024, "totalPay": 5975070, "exercisedValue": 21296796, "unexercisedValue": 30304940}, {"maxAge": 1, "name": "Dr. Robert P. Mauch Ph.D., PharmD", "age": 57, "title": "President, CEO & Director", "yearBorn": 1967, "fiscalYear": 2024, "totalPay": 3253065, "exercisedValue": 4930269, "unexercisedValue": 6275954}, {"maxAge": 1, "name": "Mr. James F. Cleary Jr.", "age": 61, "title": "Executive VP & CFO", "yearBorn": 1963, "fiscalYear": 2024, "totalPay": 2403452, "exercisedValue": 4563163, "unexercisedValue": 10866288}, {"maxAge": 1, "name": "Ms. Elizabeth S. Campbell J.D.", "age": 49, "title": "Executive VP & Chief Legal Officer", "yearBorn": 1975, "fiscalYear": 2024, "totalPay": 1968477, "exercisedValue": 586165, "unexercisedValue": 0}, {"maxAge": 1, "name": "Ms. Silvana  Battaglia", "age": 56, "title": "Executive VP & Chief Human Resources Officer", "yearBorn": 1968, "fiscalYear": 2024, "totalPay": 1719839, "exercisedValue": 496354, "unexercisedValue": 0}, {"maxAge": 1, "name": "Mr. Lazarus  Krikorian", "age": 59, "title": "Senior VP, Chief Accounting Officer & Corporate Controller", "yearBorn": 1965, "fiscalYear": 2024, "exercisedValue": 0, "unexercisedValue": 0}, {"maxAge": 1, "name": "Mr. Pawan Singh Verma", "age": 47, "title": "Executive VP and Chief Data & Information Officer", "yearBorn": 1977, "fiscalYear": 2024, "exercisedValue": 0, "unexercisedValue": 0}, {"maxAge": 1, "name": "Mr. Bennett S. Murphy", "title": "Senior VP, Head of Investor Relations & Treasury", "fiscalYear": 2024, "exercisedValue": 0, "unexercisedValue": 0}, {"maxAge": 1, "name": "Ms. Jennifer E. Dubas", "title": "Senior VP & Chief Compliance Officer", "fiscalYear": 2024, "exercisedValue": 0, "unexercisedValue": 0}, {"maxAge": 1, "name": "Mr. Richard  Tremonte", "title": "EVP and President of U.S. Pharmaceuticals & Animal Health", "fiscalYear": 2024, "exercisedValue": 0, "unexercisedValue": 0}], "auditRisk": 6, "boardRisk": 7, "compensationRisk": 2, "shareHolderRightsRisk": 7, "overallRisk": 5, "governanceEpochDate": 1754006400, "compensationAsOfEpochDate": 1735603200, "irWebsite": "http://www.amerisourcebergen.com/investor/phoenix.zhtml?c=61181&p=irol-irhome", "executiveTeam": [], "maxAge": 86400, "priceHint": 2, "previousClose": 278.4, "open": 279.03, "dayLow": 279.45, "dayHigh": 285.99, "regularMarketPreviousClose": 278.4, "regularMarketOpen": 279.03, "regularMarketDayLow": 279.45, "regularMarketDayHigh": 285.99, "dividendRate": 2.2, "dividendYield": 0.77, "exDividendDate": 1755216000, "payoutRatio": 0.2218, "fiveYearAvgDividendYield": 1.16, "beta": 0.579, "trailingPE": 29.244102, "forwardPE": 17.428484, "volume": 1106201, "regularMarketVolume": 1106201, "averageVolume": 1328985, "averageVolume10days": 1282350, "averageDailyVolume10Day": 1282350, "bid": 277.49, "ask": 302.22, "bidSize": 2, "askSize": 3, "marketCap": 55280435200, "fiftyTwoWeekLow": 218.65, "fiftyTwoWeekHigh": 309.35, "priceToSalesTrailing12Months": 0.17457657, "fiftyDayAverage": 292.3398, "twoHundredDayAverage": 265.0652, "trailingAnnualDividendRate": 2.16, "trailingAnnualDividendYield": 0.007758621, "currency": "USD", "tradeable": false, "enterpriseValue": 63425523712, "profitMargins": 0.00599, "floatShares": 183464700, "sharesOutstanding": 193878000, "sharesShort": 7128693, "sharesShortPriorMonth": 6621524, "sharesShortPreviousMonthDate": 1749772800, "dateShortInterest": 1752537600, "sharesPercentSharesOut": 0.0368, "heldPercentInsiders": 0.053049996, "heldPercentInstitutions": 0.94494003, "shortRatio": 5.32, "shortPercentOfFloat": 0.063200004, "impliedSharesOutstanding": 193878000, "bookValue": 10.215, "priceToBook": 27.912874, "lastFiscalYearEnd": 1727654400, "nextFiscalYearEnd": 1759190400, "mostRecentQuarter": 1751241600, "earningsQuarterlyGrowth": 0.422, "netIncomeToCommon": 1897255040, "trailingEps": 9.75, "forwardEps": 16.36, "lastSplitFactor": "2:1", "lastSplitDate": 1245110400, "enterpriseToRevenue": 0.2, "enterpriseToEbitda": 13.883, "52WeekChange": 0.19918406, "SandP52WeekChange": 0.19554341, "lastDividendValue": 0.55, "lastDividendDate": 1747353600, "quoteType": "EQUITY", "currentPrice": 285.13, "targetHighPrice": 355.0, "targetLowPrice": 274.0, "targetMeanPrice": 330.7857, "targetMedianPrice": 333.5, "recommendationMean": 1.6875, "recommendationKey": "buy", "numberOfAnalystOpinions": 14, "totalCash": 2231852032, "totalCashPerShare": 11.512, "ebitda": 4568678912, "totalDebt": 10147275776, "quickRatio": 0.497, "currentRatio": 0.905, "totalRevenue": 316654387200, "debtToEquity": 459.175, "revenuePerShare": 1628.807, "returnOnAssets": 0.03103, "returnOnEquity": 1.16705, "grossProfits": 10770613248, "freeCashflow": 1288606848, "operatingCashflow": 1742082048, "earningsGrowth": 0.455, "revenueGrowth": 0.087, "grossMargins": 0.03401, "ebitdaMargins": 0.0144299995, "operatingMargins": 0.012200001, "financialCurrency": "USD", "symbol": "COR", "language": "en-US", "region": "US", "typeDisp": "Equity", "quoteSourceName": "Delayed Quote", "triggerable": true, "customPriceAlertConfidence": "HIGH", "exchange": "NYQ", "messageBoardId": "finmb_24809", "exchangeTimezoneName": "America/New_York", "exchangeTimezoneShortName": "EDT", "gmtOffSetMilliseconds": -14400000, "market": "us_market", "esgPopulated": false, "fiftyDayAverageChange": -7.2098083, "fiftyDayAverageChangePercent": -0.024662424, "twoHundredDayAverageChange": 20.06482, "sourceInterval": 15, "exchangeDataDelayedBy": 0, "averageAnalystRating": "1.7 - Buy", "cryptoTradeable": false, "shortName": "Cencora, Inc.", "longName": "Cencora, Inc.", "corporateActions": [{"header": "Dividend", "message": "COR announced a cash dividend of 0.55 with an ex-date of Aug. 15, 2025", "meta": {"eventType": "DIVIDEND", "dateEpochMs": 1755230400000, "amount": "0.55"}}], "postMarketTime": 1754687100, "regularMarketTime": 1754683202, "hasPrePostMarketData": true, "firstTradeDateMilliseconds": 797002200000, "postMarketChangePercent": 0.0, "postMarketPrice": 285.13, "postMarketChange": 0.0, "regularMarketChange": 6.73001, "regularMarketDayRange": "279.45 - 285.99", "fullExchangeName": "NYSE", "averageDailyVolume3Month": 1328985, "fiftyTwoWeekLowChange": 66.48001, "fiftyTwoWeekLowChangePercent": 0.3040476, "fiftyTwoWeekRange": "218.65 - 309.35", "fiftyTwoWeekHighChange": -24.220001, "fiftyTwoWeekHighChangePercent": -0.0782932, "fiftyTwoWeekChangePercent": 19.918406, "dividendDate": 1748822400, "earningsTimestamp": 1754483400, "earningsTimestampStart": 1754483400, "earningsTimestampEnd": 1754483400, "earningsCallTimestampStart": 1754483400, "earningsCallTimestampEnd": 1754483400, "isEarningsDateEstimate": false, "epsTrailingTwelveMonths": 9.75, "epsForward": 16.36, "epsCurrentYear": 15.92355, "priceEpsCurrentYear": 17.906183, "twoHundredDayAverageChangePercent": 0.075697675, "regularMarketChangePercent": 2.41739, "regularMarketPrice": 285.13, "marketState": "CLOSED", "displayName": "Cencora", "trailingPegRatio": 0.7586}