{"address1": "1025 West NASA Boulevard", "city": "Melbourne", "state": "FL", "zip": "32919", "country": "United States", "phone": "321 727 9100", "website": "https://www.l3harris.com", "industry": "Aerospace & Defense", "industryKey": "aerospace-defense", "industryDisp": "Aerospace & Defense", "sector": "Industrials", "sectorKey": "industrials", "sectorDisp": "Industrials", "longBusinessSummary": "L3Harris Technologies, Inc. provides mission-critical solutions for government and commercial customers worldwide. It operates through Space & Airborne Systems (SAS), Integrated Mission Systems (IMS), Communication Systems (CS), and Aerojet Rocketdyne (AR) segments. The SAS segment provides satellite space payloads, sensors, and full-mission solutions; classified intelligence and cyber; airborne combat systems; and mission networks for air traffic management operations. The IMS segment offers intelligence, surveillance, and reconnaissance (ISR) systems; passive sensing and targeting; electronic attack platforms; autonomy; power and communications; networks; and sensors. The CS segment provides tactical radios, software, waveforms, satellite terminals, and end-to-end battlefield systems for the U.S. Department of Defense, international, federal, and state agency customers; broadband communications; integrated vision solutions, including helmet-mounted integrated night vision goggles with image intensifier tubes and weapon-mounted sights, aiming lasers, and range finders; and public safety radios, and system applications and equipment. The AR segment offers propulsion technologies and armament systems for strategic defense, missile defense, hypersonic, and tactical systems; and space propulsion and power systems for national security space and exploration missions. The company was formerly known as Harris Corporation and changed its name to L3Harris Technologies, Inc. in June 2019. L3Harris Technologies, Inc. was founded in 1895 and is based in Melbourne, Florida.", "fullTimeEmployees": 47000, "companyOfficers": [{"maxAge": 1, "name": "Mr. Christopher E. Kubasik CPA", "age": 63, "title": "Chairman & CEO", "yearBorn": 1961, "fiscalYear": 2024, "totalPay": 7009932, "exercisedValue": 18131388, "unexercisedValue": 17550250}, {"maxAge": 1, "name": "Mr. Kenneth L. Bedingfield", "age": 51, "title": "Senior VP, CFO & President of Aerojet Rocketdyne", "yearBorn": 1973, "fiscalYear": 2024, "totalPay": 2230969, "exercisedValue": 0, "unexercisedValue": 0}, {"maxAge": 1, "name": "Mr. Edward J. Zoiss", "age": 59, "title": "President of Space & Airborne Systems", "yearBorn": 1965, "fiscalYear": 2024, "totalPay": 1813143, "exercisedValue": 0, "unexercisedValue": 1017634}, {"maxAge": 1, "name": "Mr. Jonathan P. Rambeau", "age": 51, "title": "President of Integrated Missions Systems (IMS) Segment", "yearBorn": 1973, "fiscalYear": 2024, "totalPay": 1867180, "exercisedValue": 0, "unexercisedValue": 0}, {"maxAge": 1, "name": "Mr. Samir B. Mehta", "age": 51, "title": "President of Communication Systems Segment", "yearBorn": 1973, "fiscalYear": 2024, "totalPay": 1827317, "exercisedValue": 0, "unexercisedValue": 0}, {"maxAge": 1, "name": "Mr. David W. Zack", "title": "Vice President of Operations & Program Excellence", "fiscalYear": 2024, "exercisedValue": 0, "unexercisedValue": 0}, {"maxAge": 1, "name": "John P. Cantillon", "age": 57, "title": "VP & Principal Accounting Officer", "yearBorn": 1967, "fiscalYear": 2024, "exercisedValue": 0, "unexercisedValue": 0}, {"maxAge": 1, "name": "Dr. Andrew  Puryear", "title": "VP & CTO", "fiscalYear": 2024, "exercisedValue": 0, "unexercisedValue": 0}, {"maxAge": 1, "name": "Ms. Kimberly A. Mackenroth", "title": "VP & Chief Information Officer", "fiscalYear": 2024, "exercisedValue": 0, "unexercisedValue": 0}, {"maxAge": 1, "name": "Mr. Daniel  Gittsovich", "title": "Vice President of Investor Relations & Corporate Development", "fiscalYear": 2024, "exercisedValue": 0, "unexercisedValue": 0}], "auditRisk": 1, "boardRisk": 6, "compensationRisk": 10, "shareHolderRightsRisk": 7, "overallRisk": 9, "governanceEpochDate": 1754006400, "compensationAsOfEpochDate": 1735603200, "executiveTeam": [], "maxAge": 86400, "priceHint": 2, "previousClose": 273.81, "open": 273.73, "dayLow": 269.14, "dayHigh": 275.385, "regularMarketPreviousClose": 273.81, "regularMarketOpen": 273.73, "regularMarketDayLow": 269.14, "regularMarketDayHigh": 275.385, "dividendRate": 4.8, "dividendYield": 1.78, "exDividendDate": 1757030400, "payoutRatio": 0.5274, "fiveYearAvgDividendYield": 2.0, "beta": 0.771, "trailingPE": 30.136314, "forwardPE": 18.743572, "volume": 1639005, "regularMarketVolume": 1639005, "averageVolume": 1506669, "averageVolume10days": 1274750, "averageDailyVolume10Day": 1274750, "bid": 269.02, "ask": 270.87, "bidSize": 2, "askSize": 3, "marketCap": 50463264768, "fiftyTwoWeekLow": 193.09, "fiftyTwoWeekHigh": 280.52, "priceToSalesTrailing12Months": 2.3610754, "fiftyDayAverage": 257.8154, "twoHundredDayAverage": 230.9362, "trailingAnnualDividendRate": 4.72, "trailingAnnualDividendYield": 0.01723823, "currency": "USD", "tradeable": false, "enterpriseValue": 62083207168, "profitMargins": 0.0794, "floatShares": 186267839, "sharesOutstanding": 187095008, "sharesShort": 3528283, "sharesShortPriorMonth": 4445799, "sharesShortPreviousMonthDate": 1749772800, "dateShortInterest": 1752537600, "sharesPercentSharesOut": 0.0189, "heldPercentInsiders": 0.00336, "heldPercentInstitutions": 0.90526, "shortRatio": 2.86, "shortPercentOfFloat": 0.0216, "impliedSharesOutstanding": 187095008, "bookValue": 103.139, "priceToBook": 2.6151116, "lastFiscalYearEnd": 1735862400, "nextFiscalYearEnd": 1767398400, "mostRecentQuarter": 1750982400, "earningsQuarterlyGrowth": 0.251, "netIncomeToCommon": 1696999936, "trailingEps": 8.95, "forwardEps": 14.39, "lastSplitFactor": "10000:9448", "lastSplitDate": 1242000000, "enterpriseToRevenue": 2.905, "enterpriseToEbitda": 15.56, "52WeekChange": 0.17869163, "SandP52WeekChange": 0.19554341, "lastDividendValue": 1.2, "lastDividendDate": 1748908800, "quoteType": "EQUITY", "currentPrice": 269.72, "targetHighPrice": 327.0, "targetLowPrice": 250.0, "targetMeanPrice": 299.94736, "targetMedianPrice": 310.0, "recommendationMean": 1.72727, "recommendationKey": "buy", "numberOfAnalystOpinions": 19, "totalCash": 482000000, "totalCashPerShare": 2.576, "ebitda": 3990000128, "totalDebt": 12101999616, "quickRatio": 0.802, "currentRatio": 1.039, "totalRevenue": 21372999680, "debtToEquity": 62.776, "revenuePerShare": 113.234, "returnOnAssets": 0.04126, "returnOnEquity": 0.08926, "grossProfits": 5501000192, "freeCashflow": 2885874944, "operatingCashflow": 2507000064, "earningsGrowth": 0.271, "revenueGrowth": 0.024, "grossMargins": 0.25738, "ebitdaMargins": 0.18667999, "operatingMargins": 0.12827, "financialCurrency": "USD", "symbol": "LHX", "language": "en-US", "region": "US", "typeDisp": "Equity", "triggerable": true, "customPriceAlertConfidence": "HIGH", "regularMarketPrice": 269.72, "postMarketTime": 1754696188, "regularMarketTime": 1754683202, "marketState": "CLOSED", "regularMarketChangePercent": -1.49374, "shortName": "L3Harris Technologies, Inc.", "longName": "L3Harris Technologies, Inc.", "corporateActions": [{"header": "Dividend", "message": "LHX announced a cash dividend of 1.20 with an ex-date of Sep. 5, 2025", "meta": {"eventType": "DIVIDEND", "dateEpochMs": 1757044800000, "amount": "1.20"}}], "epsTrailingTwelveMonths": 8.95, "epsForward": 14.39, "epsCurrentYear": 10.52671, "priceEpsCurrentYear": 25.622442, "fiftyDayAverageChange": 11.904602, "fiftyDayAverageChangePercent": 0.046174906, "twoHundredDayAverageChange": 38.7838, "twoHundredDayAverageChangePercent": 0.16794161, "sourceInterval": 15, "exchangeDataDelayedBy": 0, "averageAnalystRating": "1.7 - Buy", "cryptoTradeable": false, "exchange": "NYQ", "messageBoardId": "finmb_177934", "exchangeTimezoneName": "America/New_York", "exchangeTimezoneShortName": "EDT", "gmtOffSetMilliseconds": -14400000, "market": "us_market", "esgPopulated": false, "hasPrePostMarketData": true, "firstTradeDateMilliseconds": 378657000000, "postMarketChangePercent": 0.42636582, "postMarketPrice": 270.87, "postMarketChange": 1.1499939, "regularMarketChange": -4.09, "regularMarketDayRange": "269.14 - 275.385", "fullExchangeName": "NYSE", "averageDailyVolume3Month": 1506669, "fiftyTwoWeekLowChange": 76.630005, "fiftyTwoWeekLowChangePercent": 0.3968616, "fiftyTwoWeekRange": "193.09 - 280.52", "fiftyTwoWeekHighChange": -10.799988, "fiftyTwoWeekHighChangePercent": -0.038499888, "fiftyTwoWeekChangePercent": 17.869164, "dividendDate": 1758499200, "earningsTimestamp": 1753360200, "earningsTimestampStart": 1761222600, "earningsTimestampEnd": 1761222600, "earningsCallTimestampStart": 1753367400, "earningsCallTimestampEnd": 1753367400, "isEarningsDateEstimate": true, "displayName": "L3Harris", "trailingPegRatio": 0.5798}