{"address1": "6555 State Highway 161", "city": "Irving", "state": "TX", "zip": "75039", "country": "United States", "phone": "972 446 4800", "website": "https://www.mckesson.com", "industry": "Medical Distribution", "industryKey": "medical-distribution", "industryDisp": "Medical Distribution", "sector": "Healthcare", "sectorKey": "healthcare", "sectorDisp": "Healthcare", "longBusinessSummary": "McKesson Corporation provides healthcare services in the United States and internationally. It operates through four segments: U.S. Pharmaceutical, Prescription Technology Solutions (RxTS), Medical-Surgical Solutions, and International. The U.S. Pharmaceutical segment distributes branded, generic, specialty, biosimilar and over-the-counter pharmaceutical drugs, and other healthcare-related products. This segment also provides practice management, technology, clinical support, and business solutions to community-based oncology and other specialty practices; and consulting, outsourcing, technological, and other services, as well as sells financial, operational, and clinical solutions to pharmacies. The RxTS segment serves biopharma and life sciences partners to address challenges for patients by working across healthcare to connect patients, pharmacies, providers, pharmacy benefit managers, health plans, and biopharma companies to deliver solutions to help people get the medicine needed to live healthier lives; and provides medication access and affordability, prescription decision support, prescription price transparency, benefit insight, dispensing support, third-party logistics, and wholesale distribution support services, as well as electronic prior authorization services. The Medical-Surgical Solutions segment offers medical-surgical supply distribution, logistics, biomedical maintenance, and other services to healthcare providers, including physician offices, surgery centers, nursing homes, post-acute care facilities, hospital reference labs, and home health care agencies. The International segment delivers deliver medicines, supplies, and information technology solutions to retail pharmacies, hospitals, long-term care centers, clinics and institutions; and provides logistics and distribution services for manufacturers. McKesson Corporation was founded in 1833 and is headquartered in Irving, Texas.", "fullTimeEmployees": 43000, "companyOfficers": [{"maxAge": 1, "name": "Mr. Brian S. Tyler Ph.D.", "age": 57, "title": "CEO & Director", "yearBorn": 1967, "fiscalYear": 2025, "totalPay": 5661202, "exercisedValue": 0, "unexercisedValue": 0}, {"maxAge": 1, "name": "Mr. Britt J. Vitalone CPA", "age": 54, "title": "Executive VP & CFO", "yearBorn": 1970, "fiscalYear": 2025, "totalPay": 2681328, "exercisedValue": 0, "unexercisedValue": 0}, {"maxAge": 1, "name": "Ms. Michele  Lau J.D.", "age": 48, "title": "Executive VP & Chief Legal Officer", "yearBorn": 1976, "fiscalYear": 2025, "totalPay": 2225612, "exercisedValue": 0, "unexercisedValue": 0}, {"maxAge": 1, "name": "Ms. LeAnn B. Smith", "age": 49, "title": "Executive VP & Chief Human Resources Officer", "yearBorn": 1975, "fiscalYear": 2025, "totalPay": 1516918, "exercisedValue": 0, "unexercisedValue": 0}, {"maxAge": 1, "name": "Mr. Thomas L. Rodgers M.B.A.", "age": 52, "title": "Executive VP and Chief Strategy & Business Development Officer", "yearBorn": 1972, "fiscalYear": 2025, "totalPay": 1462012, "exercisedValue": 0, "unexercisedValue": 0}, {"maxAge": 1, "name": "Mr. Napoleon B. Rutledge Jr.", "age": 52, "title": "Senior VP, Controller & Chief Accounting Officer", "yearBorn": 1972, "fiscalYear": 2025, "exercisedValue": 0, "unexercisedValue": 0}, {"maxAge": 1, "name": "Mr. Francisco  Fraga", "age": 51, "title": "Executive VP, Chief Information Officer & Chief Technology Officer", "yearBorn": 1973, "fiscalYear": 2025, "exercisedValue": 0, "unexercisedValue": 0}, {"maxAge": 1, "name": "Ms. Jeni  Dominguez", "title": "Head of Investor Relations", "fiscalYear": 2025, "exercisedValue": 0, "unexercisedValue": 0}, {"maxAge": 1, "name": "Mr. Kirk  Kaminsky", "title": "President of The US Pharmaceutical & Specialty Solutions Business", "fiscalYear": 2025, "exercisedValue": 0, "unexercisedValue": 0}, {"maxAge": 1, "name": "Paul A. Smith", "title": "Senior Vice President of Taxes", "fiscalYear": 2025, "exercisedValue": 0, "unexercisedValue": 0}], "auditRisk": 9, "boardRisk": 1, "compensationRisk": 3, "shareHolderRightsRisk": 4, "overallRisk": 2, "governanceEpochDate": 1748736000, "compensationAsOfEpochDate": 1767139200, "irWebsite": "http://www.mckesson.com/investors/stock-information/stock-information/", "executiveTeam": [], "maxAge": 86400, "priceHint": 2, "previousClose": 714.54, "open": 708.09, "dayLow": 706.1, "dayHigh": 710.79, "regularMarketPreviousClose": 714.54, "regularMarketOpen": 708.09, "regularMarketDayLow": 706.1, "regularMarketDayHigh": 710.79, "dividendRate": 2.84, "dividendYield": 0.39, "exDividendDate": 1748822400, "payoutRatio": 0.1069, "fiveYearAvgDividendYield": 0.63, "beta": 0.488, "trailingPE": 27.621254, "forwardPE": 19.277098, "volume": 364140, "regularMarketVolume": 364140, "averageVolume": 885413, "averageVolume10days": 791370, "averageDailyVolume10Day": 791370, "bid": 625.0, "ask": 725.0, "bidSize": 1, "askSize": 2, "marketCap": 88630632448, "fiftyTwoWeekLow": 464.42, "fiftyTwoWeekHigh": 737.89, "priceToSalesTrailing12Months": 0.24684691, "fiftyDayAverage": 715.1136, "twoHundredDayAverage": 626.9031, "trailingAnnualDividendRate": 2.75, "trailingAnnualDividendYield": 0.00384863, "currency": "USD", "tradeable": false, "enterpriseValue": 93782745088, "profitMargins": 0.00918, "floatShares": 124900796, "sharesOutstanding": 124904000, "sharesShort": 2006977, "sharesShortPriorMonth": 2108328, "sharesShortPreviousMonthDate": 1747267200, "dateShortInterest": 1749772800, "sharesPercentSharesOut": 0.0161, "heldPercentInsiders": 0.00062, "heldPercentInstitutions": 0.90263003, "shortRatio": 2.45, "shortPercentOfFloat": 0.0161, "impliedSharesOutstanding": 125775000, "bookValue": -16.592, "lastFiscalYearEnd": 1743379200, "nextFiscalYearEnd": 1774915200, "mostRecentQuarter": 1743379200, "earningsQuarterlyGrowth": 0.593, "netIncomeToCommon": 3295000064, "trailingEps": 25.69, "forwardEps": 36.81, "lastSplitFactor": "2:1", "lastSplitDate": 883958400, "enterpriseToRevenue": 0.261, "enterpriseToEbitda": 17.316, "52WeekChange": 0.22711241, "SandP52WeekChange": 0.1116153, "lastDividendValue": 0.71, "lastDividendDate": 1748822400, "quoteType": "EQUITY", "currentPrice": 709.59, "targetHighPrice": 820.0, "targetLowPrice": 610.0, "targetMeanPrice": 758.5707, "targetMedianPrice": 770.0, "recommendationMean": 1.70588, "recommendationKey": "buy", "numberOfAnalystOpinions": 15, "totalCash": 5690999808, "totalCashPerShare": 45.487, "ebitda": 5416000000, "totalDebt": 7414000128, "quickRatio": 0.509, "currentRatio": 0.899, "totalRevenue": 359051001856, "revenuePerShare": 2818.297, "returnOnAssets": 0.04309, "grossProfits": 12821000192, "freeCashflow": 4733250048, "operatingCashflow": 6085000192, "earningsGrowth": 0.664, "revenueGrowth": 0.189, "grossMargins": 0.03571, "ebitdaMargins": 0.01508, "operatingMargins": 0.0153, "financialCurrency": "USD", "symbol": "MCK", "language": "en-US", "region": "US", "typeDisp": "Equity", "quoteSourceName": "Delayed Quote", "triggerable": true, "customPriceAlertConfidence": "HIGH", "sourceInterval": 15, "exchangeDataDelayedBy": 0, "averageAnalystRating": "1.7 - Buy", "cryptoTradeable": false, "marketState": "PRE", "regularMarketChangePercent": -0.692747, "regularMarketPrice": 709.59, "hasPrePostMarketData": true, "firstTradeDateMilliseconds": 784477800000, "preMarketChange": -0.59002686, "preMarketChangePercent": -0.08315039, "preMarketPrice": 709.0, "regularMarketChange": -4.94995, "regularMarketDayRange": "706.1 - 710.79", "fullExchangeName": "NYSE", "averageDailyVolume3Month": 885413, "fiftyTwoWeekLowChange": 245.17001, "fiftyTwoWeekLowChangePercent": 0.52790576, "fiftyTwoWeekRange": "464.42 - 737.89", "fiftyTwoWeekHighChange": -28.299988, "fiftyTwoWeekHighChangePercent": -0.038352583, "fiftyTwoWeekChangePercent": 22.71124, "dividendDate": 1751328000, "earningsTimestamp": 1754510400, "earningsTimestampStart": 1754510400, "earningsTimestampEnd": 1754510400, "earningsCallTimestampStart": 1754512200, "earningsCallTimestampEnd": 1754512200, "isEarningsDateEstimate": false, "epsTrailingTwelveMonths": 25.69, "epsForward": 36.81, "epsCurrentYear": 37.34122, "priceEpsCurrentYear": 19.002861, "fiftyDayAverageChange": -5.5235596, "fiftyDayAverageChangePercent": -0.007724031, "twoHundredDayAverageChange": 82.68695, "twoHundredDayAverageChangePercent": 0.13189751, "priceToBook": -42.767002, "corporateActions": [], "preMarketTime": 1752480581, "regularMarketTime": 1752264002, "shortName": "McKesson Corporation", "longName": "McKesson Corporation", "exchange": "NYQ", "messageBoardId": "finmb_288195", "exchangeTimezoneName": "America/New_York", "exchangeTimezoneShortName": "EDT", "gmtOffSetMilliseconds": -14400000, "market": "us_market", "esgPopulated": false, "displayName": "McKesson", "trailingPegRatio": 1.125}