{"address1": "Building Two", "address2": "Parkmore Business Park West", "city": "Galway", "country": "Ireland", "phone": "353 1 438 1700", "website": "https://www.medtronic.com", "industry": "Medical Devices", "industryKey": "medical-devices", "industryDisp": "Medical Devices", "sector": "Healthcare", "sectorKey": "healthcare", "sectorDisp": "Healthcare", "longBusinessSummary": "Medtronic plc develops, manufactures, and sells device-based medical therapies to healthcare systems, physicians, clinicians, and patients in the United States, Ireland, and internationally. The Cardiovascular Portfolio segment offers implantable cardiac pacemakers, cardioverter defibrillators, and cardiac resynchronization therapy devices; cardiac ablation products; insertable cardiac monitor systems; TYRX products; and remote monitoring and patient-centered software. It also provides aortic valves, surgical valve replacement and repair products, endovascular stent grafts and accessories, and transcatheter pulmonary valves, and percutaneous coronary intervention products, percutaneous angioplasty balloons, and other products. The Neuroscience Portfolio segment offers medical devices and implants, biologic solutions, spinal cord stimulation and brain modulation systems, implantable drug infusion systems, and interventional products, as well as nerve ablation system under the Accurian name. The segment offers its products for spinal surgeons, neurosurgeons, neurologists, pain management specialists, anesthesiologists, orthopedic surgeons, urologists, urogynecologists, and interventional radiologists, as well as ear, nose, and throat specialists, and energy surgical instruments. The Medical Surgical Portfolio segment offers surgical stapling devices, vessel sealing instruments, wound closure and electrosurgery products, AI-powered surgical video and analytics platform, robotic-assisted surgery products, hernia mechanical devices, mesh implants, gynecology products, gastrointestinal and hepatologic diagnostics and therapies, and therapies to treat diseases and conditions, and patient monitoring and airway management products. The Diabetes Operating Unit segment provides insulin pumps and consumables, continuous glucose monitoring systems and sensors, and InPen, a smart insulin pen. Medtronic plc was founded in 1949 and is headquartered in Galway, Ireland.", "fullTimeEmployees": 95000, "companyOfficers": [{"maxAge": 1, "name": "Mr. Geoffrey Straub Martha", "age": 54, "title": "Chairman of the Board & CEO", "yearBorn": 1970, "fiscalYear": 2024, "totalPay": 3560768, "exercisedValue": 0, "unexercisedValue": 0}, {"maxAge": 1, "name": "Mr. Brett A. Wall", "age": 58, "title": "Executive VP & President of Neuroscience Portfolio", "yearBorn": 1966, "fiscalYear": 2024, "totalPay": 1754240, "exercisedValue": 0, "unexercisedValue": 0}, {"maxAge": 1, "name": "Mr. Gregory L. Smith", "age": 60, "title": "Executive Vice President of Enterprise Operations", "yearBorn": 1964, "fiscalYear": 2024, "totalPay": 1757655, "exercisedValue": 0, "unexercisedValue": 0}, {"maxAge": 1, "name": "Mr. Thierry  Pieton", "age": 54, "title": "Executive VP & CFO", "yearBorn": 1970, "fiscalYear": 2024, "exercisedValue": 0, "unexercisedValue": 0}, {"maxAge": 1, "name": "Mr. Mark  Ploof", "title": "Senior Vice President of Global Operations and Business Services", "fiscalYear": 2024, "exercisedValue": 0, "unexercisedValue": 0}, {"maxAge": 1, "name": "Ms. Denise L. Blomquist", "title": "VP, Global Controller & Chief Accounting Officer", "fiscalYear": 2024, "exercisedValue": 0, "unexercisedValue": 0}, {"maxAge": 1, "name": "Mr. Gary  Corona", "title": "Senior VP of Corporate Finance", "fiscalYear": 2024, "exercisedValue": 0, "unexercisedValue": 0}, {"maxAge": 1, "name": "Dr. Kenneth E. Washington Ph.D.", "age": 64, "title": "Senior VP and Chief Technology & Innovation Officer", "yearBorn": 1960, "fiscalYear": 2024, "exercisedValue": 0, "unexercisedValue": 0}, {"maxAge": 1, "name": "Dr. Laura  Mauri M.D., M.Sc.", "title": "Senior VP and Chief Scientific & Medical Officer", "fiscalYear": 2024, "exercisedValue": 0, "unexercisedValue": 0}, {"maxAge": 1, "name": "Mr. Ryan  Weispfenning", "title": "VP & Head of Investor Relations", "fiscalYear": 2024, "exercisedValue": 0, "unexercisedValue": 0}], "auditRisk": 7, "boardRisk": 6, "compensationRisk": 4, "shareHolderRightsRisk": 6, "overallRisk": 5, "governanceEpochDate": 1754006400, "compensationAsOfEpochDate": 1735603200, "executiveTeam": [], "maxAge": 86400, "priceHint": 2, "previousClose": 91.24, "open": 91.205, "dayLow": 91.2, "dayHigh": 92.96, "regularMarketPreviousClose": 91.24, "regularMarketOpen": 91.205, "regularMarketDayLow": 91.2, "regularMarketDayHigh": 92.96, "dividendRate": 2.84, "dividendYield": 3.06, "exDividendDate": 1750982400, "payoutRatio": 0.77559996, "fiveYearAvgDividendYield": 2.82, "beta": 0.817, "trailingPE": 25.728533, "forwardPE": 15.876923, "volume": 6446708, "regularMarketVolume": 6446708, "averageVolume": 7826285, "averageVolume10days": 6344500, "averageDailyVolume10Day": 6344500, "bid": 91.6, "ask": 93.0, "bidSize": 5, "askSize": 2, "marketCap": 119003430912, "fiftyTwoWeekLow": 79.29, "fiftyTwoWeekHigh": 96.25, "priceToSalesTrailing12Months": 3.548422, "fiftyDayAverage": 88.4476, "twoHundredDayAverage": 87.217, "trailingAnnualDividendRate": 2.8, "trailingAnnualDividendYield": 0.030688295, "currency": "USD", "tradeable": false, "enterpriseValue": 139896864768, "profitMargins": 0.13901, "floatShares": 1279086553, "sharesOutstanding": 1281260032, "sharesShort": 13065415, "sharesShortPriorMonth": 8472735, "sharesShortPreviousMonthDate": 1749772800, "dateShortInterest": 1752537600, "sharesPercentSharesOut": 0.010199999, "heldPercentInsiders": 0.00275, "heldPercentInstitutions": 0.8695, "shortRatio": 1.54, "shortPercentOfFloat": 0.010199999, "impliedSharesOutstanding": 1281260032, "bookValue": 37.462, "priceToBook": 2.4793122, "lastFiscalYearEnd": 1745539200, "nextFiscalYearEnd": 1777075200, "mostRecentQuarter": 1745539200, "earningsQuarterlyGrowth": 0.615, "netIncomeToCommon": 4662000128, "trailingEps": 3.61, "forwardEps": 5.85, "lastSplitFactor": "2:1", "lastSplitDate": 938390400, "enterpriseToRevenue": 4.171, "enterpriseToEbitda": 15.351, "52WeekChange": 0.14398324, "SandP52WeekChange": 0.19554341, "lastDividendValue": 0.71, "lastDividendDate": 1750982400, "quoteType": "EQUITY", "currentPrice": 92.88, "targetHighPrice": 112.0, "targetLowPrice": 78.0, "targetMeanPrice": 96.89808, "targetMedianPrice": 96.175, "recommendationMean": 2.06452, "recommendationKey": "buy", "numberOfAnalystOpinions": 26, "totalCash": 8965000192, "totalCashPerShare": 6.997, "ebitda": 9112999936, "totalDebt": 29625999360, "quickRatio": 1.202, "currentRatio": 1.849, "totalRevenue": 33536999424, "debtToEquity": 61.393, "revenuePerShare": 26.087, "returnOnAssets": 0.044060003, "returnOnEquity": 0.09508, "grossProfits": 21930999808, "freeCashflow": 4206249984, "operatingCashflow": 7043999744, "earningsGrowth": 0.68, "revenueGrowth": 0.039, "grossMargins": 0.65392995, "ebitdaMargins": 0.27173, "operatingMargins": 0.17094, "financialCurrency": "USD", "symbol": "MDT", "language": "en-US", "region": "US", "typeDisp": "Equity", "quoteSourceName": "Delayed Quote", "triggerable": true, "customPriceAlertConfidence": "HIGH", "shortName": "Medtronic plc.", "longName": "Medtronic plc", "hasPrePostMarketData": true, "firstTradeDateMilliseconds": 105197400000, "postMarketChangePercent": 0.34453025, "postMarketPrice": 93.2, "postMarketChange": 0.3199997, "regularMarketChange": 1.64, "regularMarketDayRange": "91.2 - 92.96", "fullExchangeName": "NYSE", "averageDailyVolume3Month": 7826285, "fiftyTwoWeekLowChange": 13.589996, "fiftyTwoWeekLowChangePercent": 0.17139609, "fiftyTwoWeekRange": "79.29 - 96.25", "fiftyTwoWeekHighChange": -3.3700027, "fiftyTwoWeekHighChangePercent": -0.035013016, "fiftyTwoWeekChangePercent": 14.398325, "priceEpsCurrentYear": 16.73233, "fiftyDayAverageChange": 4.432396, "fiftyDayAverageChangePercent": 0.050113242, "twoHundredDayAverageChange": 5.6629944, "sourceInterval": 15, "exchangeDataDelayedBy": 0, "averageAnalystRating": "2.1 - Buy", "cryptoTradeable": false, "regularMarketChangePercent": 1.79746, "regularMarketPrice": 92.88, "corporateActions": [], "postMarketTime": 1754697600, "regularMarketTime": 1754683202, "exchange": "NYQ", "messageBoardId": "finmb_31348", "exchangeTimezoneName": "America/New_York", "exchangeTimezoneShortName": "EDT", "gmtOffSetMilliseconds": -14400000, "market": "us_market", "esgPopulated": false, "marketState": "CLOSED", "dividendDate": 1752192000, "earningsTimestamp": 1755576000, "earningsTimestampStart": 1755576000, "earningsTimestampEnd": 1755576000, "earningsCallTimestampStart": 1755604800, "earningsCallTimestampEnd": 1755604800, "isEarningsDateEstimate": false, "epsTrailingTwelveMonths": 3.61, "epsForward": 5.85, "epsCurrentYear": 5.55093, "twoHundredDayAverageChangePercent": 0.06492993, "displayName": "Medtronic", "trailingPegRatio": 2.1809}