{"address1": "100 Nagog Park", "city": "Acton", "state": "MA", "zip": "01720", "country": "United States", "phone": "978 600 7000", "website": "https://www.insulet.com", "industry": "Medical Devices", "industryKey": "medical-devices", "industryDisp": "Medical Devices", "sector": "Healthcare", "sectorKey": "healthcare", "sectorDisp": "Healthcare", "longBusinessSummary": "Insulet Corporation develops, manufactures, and sells insulin delivery systems for people with insulin-dependent diabetes in the United States and internationally. The company offers Omnipod platform products comprising Omnipod 5 automated insulin delivery system, which includes a proprietary AID algorithm embedded in the pod that integrates with a third-party continuous glucose monitor to obtain glucose values through wireless Bluetooth communication; and Omnipod DASH insulin management system that features a Bluetooth enabled pod that is controlled by a smartphone-like personal diabetes manager with a color touch screen user interface. It also provides pods for Amgen for use in the Neulasta Onpro kit, which is a delivery system to help reduce the risk of infection after intense chemotherapy. The company sells its products to end-users through the pharmacy channel; and independent distributors. Insulet Corporation was incorporated in 2000 and is headquartered in Acton, Massachusetts.", "fullTimeEmployees": 3900, "companyOfficers": [{"maxAge": 1, "name": "Ms. Ana Maria Chadwick", "age": 52, "title": "Executive VP & CFO", "yearBorn": 1972, "fiscalYear": 2024, "totalPay": 1081078, "exercisedValue": 0, "unexercisedValue": 0}], "auditRisk": 5, "boardRisk": 4, "compensationRisk": 8, "shareHolderRightsRisk": 10, "overallRisk": 9, "governanceEpochDate": 1754006400, "compensationAsOfEpochDate": 1735603200, "irWebsite": "http://investor.insulet.com/index.cfm", "executiveTeam": [], "maxAge": 86400, "priceHint": 2, "previousClose": 303.55, "open": 303.55, "dayLow": 299.83, "dayHigh": 312.99, "regularMarketPreviousClose": 303.55, "regularMarketOpen": 303.55, "regularMarketDayLow": 299.83, "regularMarketDayHigh": 312.99, "payoutRatio": 0.0, "beta": 1.348, "trailingPE": 93.34347, "forwardPE": 79.35401, "volume": 1099677, "regularMarketVolume": 1099677, "averageVolume": 770343, "averageVolume10days": 787140, "averageDailyVolume10Day": 787140, "bid": 286.24, "ask": 332.8, "bidSize": 2, "askSize": 2, "marketCap": 21617534976, "fiftyTwoWeekLow": 180.31, "fiftyTwoWeekHigh": 329.33, "priceToSalesTrailing12Months": 9.831068, "fiftyDayAverage": 300.0402, "twoHundredDayAverage": 275.87476, "trailingAnnualDividendRate": 0.0, "trailingAnnualDividendYield": 0.0, "currency": "USD", "tradeable": false, "enterpriseValue": 19980466176, "profitMargins": 0.18291001, "floatShares": 70079348, "sharesOutstanding": 70392496, "sharesShort": 2122903, "sharesShortPriorMonth": 1906067, "sharesShortPreviousMonthDate": 1749772800, "dateShortInterest": 1752537600, "sharesPercentSharesOut": 0.030199999, "heldPercentInsiders": 0.0028600001, "heldPercentInstitutions": 1.0288501, "shortRatio": 2.79, "shortPercentOfFloat": 0.045900002, "impliedSharesOutstanding": 70392496, "bookValue": 20.783, "priceToBook": 14.7765, "lastFiscalYearEnd": 1735603200, "nextFiscalYearEnd": 1767139200, "mostRecentQuarter": 1743379200, "earningsQuarterlyGrowth": -0.313, "netIncomeToCommon": 402200000, "trailingEps": 3.29, "forwardEps": 3.87, "enterpriseToRevenue": 9.087, "enterpriseToEbitda": 47.068, "52WeekChange": 0.6330763, "SandP52WeekChange": 0.19554341, "quoteType": "EQUITY", "currentPrice": 307.1, "targetHighPrice": 400.0, "targetLowPrice": 266.0, "targetMeanPrice": 351.91302, "targetMedianPrice": 353.0, "recommendationMean": 1.45833, "recommendationKey": "strong_buy", "numberOfAnalystOpinions": 23, "totalCash": 1283100032, "totalCashPerShare": 18.232, "ebitda": 424500000, "totalDebt": 1748600064, "quickRatio": 3.239, "currentRatio": 4.474, "totalRevenue": 2198899968, "debtToEquity": 131.405, "revenuePerShare": 31.344, "returnOnAssets": 0.06937, "returnOnEquity": 0.37917998, "grossProfits": 1547900032, "freeCashflow": 84250000, "operatingCashflow": 406500000, "earningsGrowth": -0.316, "revenueGrowth": 0.288, "grossMargins": 0.70394, "ebitdaMargins": 0.19305, "operatingMargins": 0.15606, "financialCurrency": "USD", "symbol": "PODD", "language": "en-US", "region": "US", "typeDisp": "Equity", "quoteSourceName": "Nasdaq Real Time Price", "triggerable": true, "customPriceAlertConfidence": "HIGH", "regularMarketChangePercent": 1.1695, "regularMarketPrice": 307.1, "postMarketChangePercent": -0.683818, "postMarketPrice": 305.0, "postMarketChange": -2.10001, "regularMarketChange": 3.55002, "regularMarketDayRange": "299.83 - 312.99", "fullExchangeName": "NasdaqGS", "averageDailyVolume3Month": 770343, "fiftyTwoWeekLowChange": 126.79001, "fiftyTwoWeekLowChangePercent": 0.7031779, "fiftyTwoWeekRange": "180.31 - 329.33", "fiftyTwoWeekHighChange": -22.22998, "fiftyTwoWeekHighChangePercent": -0.06750063, "fiftyTwoWeekChangePercent": 63.307632, "earningsTimestamp": 1754539200, "earningsTimestampStart": 1762432200, "earningsTimestampEnd": 1762432200, "earningsCallTimestampStart": 1754568000, "earningsCallTimestampEnd": 1754568000, "isEarningsDateEstimate": true, "epsTrailingTwelveMonths": 3.29, "epsForward": 3.87, "epsCurrentYear": 4.55319, "priceEpsCurrentYear": 67.44722, "fiftyDayAverageChange": 7.0598145, "fiftyDayAverageChangePercent": 0.023529563, "twoHundredDayAverageChange": 31.22525, "twoHundredDayAverageChangePercent": 0.11318633, "sourceInterval": 15, "exchangeDataDelayedBy": 0, "averageAnalystRating": "1.5 - Strong Buy", "cryptoTradeable": false, "hasPrePostMarketData": true, "firstTradeDateMilliseconds": 1179235800000, "corporateActions": [], "postMarketTime": 1754688181, "regularMarketTime": 1754683200, "exchange": "NMS", "messageBoardId": "finmb_618908", "exchangeTimezoneName": "America/New_York", "exchangeTimezoneShortName": "EDT", "gmtOffSetMilliseconds": -14400000, "market": "us_market", "esgPopulated": false, "shortName": "Insulet Corporation", "longName": "Insulet Corporation", "marketState": "CLOSED", "displayName": "Insulet", "trailingPegRatio": 4.3814}